lokesh/__init__.py
lokesh/some_module.py
lokesh-0.1.dist-info/METADATA
lokesh-0.1.dist-info/WHEEL
lokesh-0.1.dist-info/top_level.txt
lokesh-0.1.dist-info/RECORD
